{
  "user": {
    "id": "jBWMVGjm50l6LGwepDoty",
    "username": "frontendmaster"
  },
  "pet": [
    {
      "id": "2l3krjhwelkfhaiewua",
      "type": "CAT",
      "img": "img.jpg",
      "name": "Tom",
      "createdAt": 1241234
    },
    {
      "id": "9mzUSlFLb3RdzF-jgFC9Z",
      "createdAt": 1620240831537,
      "name": "James",
      "type": "DOG",
      "user": "jBWMVGjm50l6LGwepDoty"
    },
    {
      "id": "ruF5fMAZUpnsfiq0U18CY",
      "createdAt": 1620240997686,
      "name": "Alfie",
      "type": "DOG",
      "user": "jBWMVGjm50l6LGwepDoty"
    },
    {
      "id": "93ZhxreIYy9cKHKRdsu4E",
      "createdAt": 1620329419561,
      "name": "Samantha",
      "type": "CAT",
      "user": "jBWMVGjm50l6LGwepDoty"
    },
    {
      "id": "Z1eIDFBdnswDSwCNXPGhG",
      "createdAt": 1620329789857,
      "name": "Jimmy",
      "type": "DOG",
      "user": "jBWMVGjm50l6LGwepDoty"
    },
    {
      "id": "pOP7IyshPRxA9qXuL-VL2",
      "createdAt": 1620330165651,
      "name": "David",
      "type": "DOG",
      "user": "jBWMVGjm50l6LGwepDoty"
    },
    {
      "id": "ucOfTjCBmtwGR6esKtb_i",
      "createdAt": 1620330247863,
      "name": "Jennifer",
      "type": "CAT",
      "user": "jBWMVGjm50l6LGwepDoty"
    },
    {
      "id": "owsWg_qTYBMHL8eahb3lf",
      "createdAt": 1620330270959,
      "name": "Daniel",
      "type": "DOG",
      "user": "jBWMVGjm50l6LGwepDoty"
    },
    {
      "id": "_0d7GF0z0bfHBux4V_IWB",
      "createdAt": 1620330291975,
      "name": "Superman",
      "type": "DOG",
      "user": "jBWMVGjm50l6LGwepDoty"
    },
    {
      "id": "rKe7OvhC5N1qtwzQ5_-DI",
      "createdAt": 1620330397189,
      "name": "Diva",
      "type": "CAT",
      "user": "jBWMVGjm50l6LGwepDoty"
    },
    {
      "id": "s7k7sFwwkCG4204PlWjBi",
      "createdAt": 1620331001383,
      "name": "Angelica",
      "type": "CAT",
      "user": "jBWMVGjm50l6LGwepDoty"
    },
    {
      "id": "b4RzB40MhgstiDtM5mjsn",
      "createdAt": 1620331128350,
      "name": "Aflie",
      "type": "DOG",
      "user": "jBWMVGjm50l6LGwepDoty"
    },
    {
      "id": "dyqn6-_8r8fXTEKoBggi0",
      "createdAt": 1620331240215,
      "name": "Lucy",
      "type": "CAT",
      "user": "jBWMVGjm50l6LGwepDoty"
    },
    {
      "id": "TS95vYKvp-VQPac4EGsv_",
      "createdAt": 1620346609668,
      "name": "Jimmy",
      "type": "CAT",
      "user": "jBWMVGjm50l6LGwepDoty"
    },
    {
      "id": "3s28jzIVs933PmDLt-5Y7",
      "createdAt": 1620348827448,
      "name": "Alfred",
      "type": "DOG",
      "user": "jBWMVGjm50l6LGwepDoty"
    },
    {
      "id": "cf5_kzh_SbcPVSDgfXOy4",
      "createdAt": 1620348860333,
      "name": "Jemiriqai",
      "type": "CAT",
      "user": "jBWMVGjm50l6LGwepDoty"
    },
    {
      "id": "lcahqadZyLoArjZrjiI-p",
      "createdAt": 1620348898847,
      "name": "Angelina",
      "type": "DOG",
      "user": "jBWMVGjm50l6LGwepDoty"
    },
    {
      "id": "Z3MSzs6wcQyd3QfW_0opW",
      "createdAt": 1620348927449,
      "name": "Sunny",
      "type": "CAT",
      "user": "jBWMVGjm50l6LGwepDoty"
    }
  ]
}